umihico/__init__.py
umihico/api/__init__.py
umihico/api/line.py
umihico/aws/__init__.py
umihico/aws/dynamodb.py
umihico/aws/iam.py
umihico/aws/lambda_.py
umihico/aws/s3.py
umihico/hash_/__init__.py
umihico/io_/__init__.py
umihico/listing/__init__.py
umihico/scraping/__init__.py
umihico/scraping/chrome.py
umihico/scraping/lxml_.py
umihico/scraping/requests_.py
umihico/string/__init__.py
umihico/xlsx/__init__.py
umihico/zip/__init__.py
umihico-0.4.7.dist-info/METADATA
umihico-0.4.7.dist-info/RECORD
umihico-0.4.7.dist-info/WHEEL
umihico-0.4.7.dist-info/top_level.txt
