Metadata-Version: 2.1
Name: umihico
Version: 0.4.7
Summary: my common functions
Home-page: https://github.com/umihico/umihico
Author: umihico
Author-email: umihico_dummy@users.noreply.github.com
License: MIT
Keywords: umihico
Platform: UNKNOWN
Classifier: Programming Language :: Python :: 3.6
Requires-Dist: requests
Requires-Dist: boto3
Requires-Dist: selenium
Requires-Dist: xlsxwriter
Requires-Dist: xlrd
